{"slideshow_credits": null, "snippet": "Terry Tang, whose career at The New York Times has included stints on the metropolitan, business and editorial desks, has been named deputy editorial page editor.", "abstract": "The New York Times names Terry Tang deputy editorial page editor.", "section_name": "Business Day", "print_page": "2", "document_type": "article", "byline": {"person": [], "organization": "THE NEW YORK TIMES", "original": "By THE NEW YORK TIMES", "contributor": ""}, "web_url": "http://www.nytimes.com/2012/08/09/business/media/terry-tang-is-named-deputy-editorial-page-editor-at-the-times.html", "lead_paragraph": "Terry Tang, whose career at The New York Times has included stints on the metropolitan, business and editorial desks, has been named deputy editorial page editor.", "headline": {"seo": "Terry Tang Is Named Deputy Editorial Page Editor at The Times", "main": "Editorial Page Promotion at The Times", "print_headline": "Editorial Page Promotion At The Times"}, "_id": "53f9a4c638f0d84410bcb1d8", "word_count": "233", "multimedia": [], "pub_date": "2012-08-09T00:00:00Z", "source": "The New York Times", "news_desk": "Business", "keywords": [{"value": "New York Times", "name": "organizations", "is_major": "Y", "rank": "1"}, {"value": "Newspapers", "name": "subject", "is_major": "N", "rank": "2"}, {"value": "Tang, Terry A", "name": "persons", "is_major": "Y", "rank": "3"}, {"value": "Appointments and Executive Changes", "name": "subject", "is_major": "N", "rank": "4"}], "blog": [], "subsection_name": "Media", "type_of_material": "News"}