{"slideshow_credits": null, "snippet": "Photos from India, Gaza Strip, Turkey and Lebanon.", "abstract": "Photos from India, Gaza Strip, Turkey and Lebanon.", "section_name": "Multimedia", "print_page": null, "document_type": "blogpost", "byline": {"person": [], "original": "By THE NEW YORK TIMES", "organization": "The New York Times"}, "web_url": "http://lens.blogs.nytimes.com/2012/09/06/pictures-of-the-day-india-and-elsewhere-20/", "lead_paragraph": null, "headline": {"main": "Pictures of the Day: India and Elsewhere", "kicker": "Lens"}, "_id": "504a67df1c22dfde670b8e4e", "word_count": "14", "multimedia": [], "pub_date": "2012-09-06T16:28:16Z", "source": "The New York Times", "news_desk": null, "keywords": [], "blog": [], "subsection_name": null, "type_of_material": "Blog"}