{"slideshow_credits": null, "snippet": "Subjects include the 11th anniversary of 9/11, a controversial circumcision ritual and the New York primary race.", "abstract": "Subjects include the 11th anniversary of 9/11, a controversial circumcision ritual and the New York primary race.", "section_name": "N.Y. / Region", "print_page": null, "document_type": "blogpost", "byline": {"person": [], "original": "By THE NEW YORK TIMES", "organization": "The New York Times"}, "web_url": "http://cityroom.blogs.nytimes.com/2012/09/14/week-in-pictures-for-sept-14/", "lead_paragraph": null, "headline": {"main": "Week in Pictures for Sept. 14", "kicker": "City Room"}, "_id": "5053a59e1c22dfde670c89f8", "word_count": "0", "multimedia": [{"height": 126, "url": "images/2012/09/14/nyregion/20120914wip/20120914wip-thumbWide.jpg", "legacy": {"wideheight": "126", "wide": "images/2012/09/14/nyregion/20120914wip/20120914wip-thumbWide.jpg", "widewidth": "190"}, "subtype": "wide", "width": 190, "type": "image"}, {"height": 75, "url": "images/2012/09/14/nyregion/20120914wip/20120914wip-thumbStandard.jpg", "legacy": {"thumbnail": "images/2012/09/14/nyregion/20120914wip/20120914wip-thumbStandard.jpg", "thumbnailwidth": "75", "thumbnailheight": "75"}, "subtype": "thumbnail", "width": 75, "type": "image"}], "pub_date": "2012-09-14T17:33:44Z", "source": "The New York Times", "news_desk": null, "keywords": [{"name": "glocations", "value": "New York City", "rank": "1"}, {"name": "subject", "value": "Photography", "rank": "1"}], "blog": [], "subsection_name": null, "type_of_material": "Blog"}