{"slideshow_credits": null, "snippet": "The hefty increases raise legitimate concerns about the country&#8217;s intentions that Beijing should seek to dispel.", "abstract": "Editorial contends China's increased defense budget raises legitimate concerns about its motives, especially at a time when regional tensions are rising; urges Congress to resist impulse to pump up military spending in response; calls for expanding Pres Obama's policy of expanding America's engagement in Asia while remaining cleareyed about China's capabilities.", "section_name": "Opinion", "print_page": "20", "document_type": "article", "byline": {"person": [], "organization": "THE EDITORIAL BOARD", "original": "By THE EDITORIAL BOARD", "contributor": ""}, "web_url": "http://www.nytimes.com/2014/03/10/opinion/chinas-disturbing-defense-budget.html", "lead_paragraph": "The hefty increases raise legitimate concerns about the country&#8217;s intentions that Beijing should seek to dispel.", "headline": {"main": "China\u2019s Disturbing Defense Budget", "print_headline": "China\u2019s Disturbing Defense Budget", "content_kicker": "Editorial", "kicker": "Editorial"}, "_id": "531d107e38f0d85d201f7726", "word_count": "439", "multimedia": [], "pub_date": "2014-03-10T00:00:00Z", "source": "The New York Times", "news_desk": "Editorial", "keywords": [{"value": "United States International Relations", "name": "subject", "is_major": "N", "rank": "4"}, {"value": "Defense and Military Forces", "name": "subject", "is_major": "N", "rank": "2"}, {"value": "Editorials", "name": "subject", "is_major": "Y", "rank": "5"}, {"value": "China", "name": "glocations", "is_major": "Y", "rank": "1"}, {"value": "Budgets and Budgeting", "name": "subject", "is_major": "N", "rank": "3"}], "blog": [], "subsection_name": null, "type_of_material": "Editorial"}