{"review_count": 56, "image_url": "https://s3-media1.fl.yelpcdn.com/bphoto/G3VGDdXL1A8R4tD5BkDmEA/o.jpg", "rating": 3.5, "coordinates": {"longitude": -71.1218338, "latitude": 42.3724213}, "phone": "+16176615000", "categories": [{"alias": "jazzandblues", "title": "Jazz & Blues"}], "location": {"city": "Cambridge", "address3": "", "country": "US", "address1": "1 Bennett St", "address2": "", "zip_code": "02138", "state": "MA"}, "price": "$$", "is_closed": false, "photos": ["https://s3-media1.fl.yelpcdn.com/bphoto/G3VGDdXL1A8R4tD5BkDmEA/o.jpg", "https://s3-media1.fl.yelpcdn.com/bphoto/eRC2RrQ5R6BcwR-Upy7lUQ/o.jpg", "https://s3-media3.fl.yelpcdn.com/bphoto/5CWIXpdF3-4ISuquA6_bKQ/o.jpg"], "url": "https://www.yelp.com/biz/regattabar-jazz-club-cambridge?adjust_creative=92p07_JjKyriZTQxAXRiKQ&utm_campaign=yelp_api_v3&utm_medium=api_v3_business_lookup&utm_source=92p07_JjKyriZTQxAXRiKQ", "id": "regattabar-jazz-club-cambridge", "term": "attractions", "hours": [{"hours_type": "REGULAR", "is_open_now": true, "open": [{"end": "0000", "start": "1600", "is_overnight": false, "day": 1}, {"end": "0000", "start": "1600", "is_overnight": false, "day": 2}, {"end": "0000", "start": "1600", "is_overnight": false, "day": 3}, {"end": "0000", "start": "1600", "is_overnight": false, "day": 4}, {"end": "0000", "start": "1600", "is_overnight": false, "day": 5}, {"end": "0000", "start": "1600", "is_overnight": false, "day": 6}]}], "name": "Regattabar Jazz Club", "is_claimed": true}