{"slideshow_credits": null, "snippet": "More and more fourth and fifth graders in New York City are being tutored for their standardized tests.", "abstract": "More and more fourth and fifth graders in New York City are being tutored for their standardized tests.", "section_name": "Style", "print_page": null, "document_type": "blogpost", "byline": {"person": [], "original": "By THE NEW YORK TIMES", "organization": "The New York Times"}, "web_url": "http://parenting.blogs.nytimes.com/2012/04/16/in-n-y-c-tutoring-intensifies-in-race-to-middle-school/", "lead_paragraph": null, "headline": {"main": "In New York, Tutoring Intensifies in Race to Middle School", "kicker": "Motherlode Blog"}, "_id": "4fd3a3bf8eb7c8105d8ed7d1", "word_count": "64", "multimedia": [], "pub_date": "2012-04-16T11:00:00Z", "source": "The New York Times", "news_desk": null, "keywords": [], "blog": [], "subsection_name": null, "type_of_material": "Blog"}