{"review_count": 8, "image_url": "https://s3-media3.fl.yelpcdn.com/bphoto/tFVbj98JrMe3koYpFf7Lcg/o.jpg", "rating": 3.5, "coordinates": {"longitude": -4.25545869256803, "latitude": 55.880160707181}, "phone": "+441413316105", "categories": [{"alias": "chinese", "title": "Chinese"}], "location": {"city": "Glasgow", "address3": "Hamilton Hill", "country": "GB", "address1": "The Point", "address2": "29 Saracen Street", "zip_code": "G22 5HT", "state": "GLG"}, "price": "\u00a3\u00a3", "is_closed": false, "photos": ["https://s3-media3.fl.yelpcdn.com/bphoto/tFVbj98JrMe3koYpFf7Lcg/o.jpg", "https://s3-media2.fl.yelpcdn.com/bphoto/-u2MjbUiqacW0XpAJWZGgg/o.jpg", "https://s3-media4.fl.yelpcdn.com/bphoto/HilFacEatcC32Tsq43YzOA/o.jpg"], "url": "https://www.yelp.com/biz/seewoo-restaurant-glasgow-2?adjust_creative=92p07_JjKyriZTQxAXRiKQ&utm_campaign=yelp_api_v3&utm_medium=api_v3_business_lookup&utm_source=92p07_JjKyriZTQxAXRiKQ", "id": "seewoo-restaurant-glasgow-2", "term": "restaurants", "hours": [{"hours_type": "REGULAR", "is_open_now": false, "open": [{"end": "2230", "start": "1200", "is_overnight": false, "day": 0}, {"end": "2230", "start": "1200", "is_overnight": false, "day": 1}, {"end": "2230", "start": "1200", "is_overnight": false, "day": 2}, {"end": "2230", "start": "1200", "is_overnight": false, "day": 3}, {"end": "2230", "start": "1200", "is_overnight": false, "day": 4}, {"end": "2230", "start": "1200", "is_overnight": false, "day": 5}, {"end": "2230", "start": "1200", "is_overnight": false, "day": 6}]}], "name": "SeeWoo Restaurant", "is_claimed": false}