{"slideshow_credits": null, "snippet": "By late summer, 1,700 conductors will be using the Apple devices to scan tickets electronically and do much more.", "abstract": "By late summer, 1,700 conductors will be using the Apple devices to scan tickets electronically and do much more.", "section_name": "Technology", "print_page": null, "document_type": "blogpost", "byline": {"person": [], "original": "By THE NEW YORK TIMES", "organization": "The New York Times"}, "web_url": "http://bits.blogs.nytimes.com/2012/05/07/amtrak-enlists-iphones-as-a-service-tool/", "lead_paragraph": null, "headline": {"main": "Amtrak Enlists iPhones as a Service Tool", "kicker": "bits"}, "_id": "4fd3a4a18eb7c8105d8ef649", "word_count": "22", "multimedia": [], "pub_date": "2012-05-07T08:39:02Z", "source": "The New York Times", "news_desk": null, "keywords": [], "blog": [], "subsection_name": null, "type_of_material": "Blog"}