{"review_count": 65, "image_url": "https://s3-media2.fl.yelpcdn.com/bphoto/knZujrFXFO9N3SouL4cojA/o.jpg", "rating": 4.5, "coordinates": {"longitude": -122.34165, "latitude": 47.61203}, "phone": "+12064481111", "categories": [{"alias": "hotels", "title": "Hotels"}, {"alias": "venues", "title": "Venues & Event Spaces"}, {"alias": "eventplanning", "title": "Party & Event Planning"}], "location": {"city": "Seattle", "address3": "", "address2": "", "state": "WA", "address1": "2000 2nd Ave", "zip_code": "98121", "country": "US"}, "price": "$$$", "is_closed": false, "photos": ["https://s3-media4.fl.yelpcdn.com/bphoto/9ZwewBkqMi7A1nSk4ls5sw/o.jpg", "https://s3-media2.fl.yelpcdn.com/bphoto/eV1s7ejIEiS0OMbrzLaQyw/o.jpg", "https://s3-media3.fl.yelpcdn.com/bphoto/Xv0j6cl-upyo3PBUZmABLg/o.jpg"], "url": "https://www.yelp.com/biz/kimpton-palladian-hotel-seattle?adjust_creative=92p07_JjKyriZTQxAXRiKQ&utm_campaign=yelp_api_v3&utm_medium=api_v3_business_lookup&utm_source=92p07_JjKyriZTQxAXRiKQ", "id": "kimpton-palladian-hotel-seattle", "term": "attractions", "is_claimed": true, "name": "Kimpton Palladian Hotel", "hours": [{"hours_type": "REGULAR", "is_open_now": true, "open": [{"end": "0000", "start": "0000", "is_overnight": false, "day": 0}, {"end": "0000", "start": "0000", "is_overnight": false, "day": 1}, {"end": "0000", "start": "0000", "is_overnight": false, "day": 2}, {"end": "0000", "start": "0000", "is_overnight": false, "day": 3}, {"end": "0000", "start": "0000", "is_overnight": false, "day": 4}, {"end": "0000", "start": "0000", "is_overnight": false, "day": 5}, {"end": "0000", "start": "0000", "is_overnight": false, "day": 6}]}]}