{"review_count": 175, "image_url": "https://s3-media2.fl.yelpcdn.com/bphoto/N7LcR3bhAVZhHMWJVRqZQw/o.jpg", "rating": 4.5, "coordinates": {"longitude": -112.1027159, "latitude": 33.5238451}, "phone": "+16029737003", "categories": [{"alias": "fishnchips", "title": "Fish & Chips"}, {"alias": "bbq", "title": "Barbeque"}], "location": {"city": "Phoenix", "address3": "", "country": "US", "address1": "2019 W Bethany Home Rd", "address2": "", "zip_code": "85015", "state": "AZ"}, "price": "$", "is_closed": false, "photos": ["https://s3-media3.fl.yelpcdn.com/bphoto/N7LcR3bhAVZhHMWJVRqZQw/o.jpg", "https://s3-media3.fl.yelpcdn.com/bphoto/qHk4331itsqWQ0Q-GVMnJA/o.jpg", "https://s3-media1.fl.yelpcdn.com/bphoto/HGddCRJ3i-GFilIQQ_0tZg/o.jpg"], "url": "https://www.yelp.com/biz/papa-joes-fish-n-que-phoenix?adjust_creative=92p07_JjKyriZTQxAXRiKQ&utm_campaign=yelp_api_v3&utm_medium=api_v3_business_lookup&utm_source=92p07_JjKyriZTQxAXRiKQ", "id": "papa-joes-fish-n-que-phoenix", "term": "restaurants", "is_claimed": true, "name": "Papa Joe's Fish-N-Que", "hours": [{"hours_type": "REGULAR", "is_open_now": false, "open": [{"end": "2000", "start": "1030", "is_overnight": false, "day": 0}, {"end": "2000", "start": "1030", "is_overnight": false, "day": 1}, {"end": "2000", "start": "1030", "is_overnight": false, "day": 2}, {"end": "2000", "start": "1030", "is_overnight": false, "day": 3}, {"end": "2000", "start": "1030", "is_overnight": false, "day": 4}, {"end": "2000", "start": "1100", "is_overnight": false, "day": 5}]}]}