{"review_count": 7, "image_url": "https://s3-media1.fl.yelpcdn.com/bphoto/pKWh_ZT6i0tqHlCb3EzHwg/o.jpg", "rating": 5.0, "coordinates": {"longitude": -82.6403477, "latitude": 27.7715589}, "categories": [{"alias": "eventphotography", "title": "Event Photography"}, {"alias": "sessionphotography", "title": "Session Photography"}], "location": {"city": "St. Petersburg", "address3": "", "country": "US", "address1": "10 5th St N", "address2": "Studio 210 A", "zip_code": "33701", "state": "FL"}, "phone": "+17277442254", "is_closed": false, "photos": ["https://s3-media1.fl.yelpcdn.com/bphoto/pKWh_ZT6i0tqHlCb3EzHwg/o.jpg", "https://s3-media1.fl.yelpcdn.com/bphoto/zEl5K6_T71G5ZLFCJ-kGDQ/o.jpg", "https://s3-media2.fl.yelpcdn.com/bphoto/mXI7ethi2pXa3jlWqC0kgw/o.jpg"], "url": "https://www.yelp.com/biz/brian-james-gallery-photography-st-petersburg?adjust_creative=92p07_JjKyriZTQxAXRiKQ&utm_campaign=yelp_api_v3&utm_medium=api_v3_business_lookup&utm_source=92p07_JjKyriZTQxAXRiKQ", "id": "brian-james-gallery-photography-st-petersburg", "term": "attractions", "hours": [{"hours_type": "REGULAR", "is_open_now": false, "open": [{"end": "1800", "start": "1000", "is_overnight": false, "day": 0}, {"end": "1800", "start": "1000", "is_overnight": false, "day": 1}, {"end": "1800", "start": "1000", "is_overnight": false, "day": 2}, {"end": "1800", "start": "1000", "is_overnight": false, "day": 3}, {"end": "1800", "start": "1000", "is_overnight": false, "day": 4}]}], "name": "Brian James Gallery Photography", "is_claimed": true}