{"slideshow_credits": null, "snippet": "Every day on NYTimes.com you can solve a new sudoku puzzle that matches your level of expertise.", "abstract": null, "section_name": "Crosswords & Games", "print_page": null, "document_type": "multimedia", "byline": [], "web_url": "http://www.nytimes.com/interactive/crosswords/sudoku-puzzle-easy.html", "lead_paragraph": "Every day on NYTimes.com you can solve a new sudoku puzzle that matches your level of expertise.", "headline": {"main": "Sudoku \u2014 Easy"}, "_id": "52b3580f38f0d867be2da6dd", "word_count": "278", "multimedia": [], "pub_date": "2014-01-21T15:24:05Z", "source": "The New York Times", "news_desk": "Crosswords & Games", "keywords": [], "blog": [], "subsection_name": null, "type_of_material": "Interactive Feature"}