{"slideshow_credits": null, "snippet": "A diagram provided by Ford illustrates its new solar technology.", "abstract": null, "section_name": "Business Day", "print_page": null, "document_type": "multimedia", "byline": [], "web_url": "http://www.nytimes.com/video/business/100000002630057/cmax-solar-technology.html", "lead_paragraph": "A diagram provided by Ford illustrates its new solar technology.", "headline": {"main": "CMAX Solar Technology"}, "_id": "52c5ed5238f0d82ae415db78", "word_count": "10", "multimedia": [{"height": 126, "url": "images/2014/01/02/multimedia/ford-solar/ford-solar-thumbWide.jpg", "legacy": {"wideheight": "126", "wide": "images/2014/01/02/multimedia/ford-solar/ford-solar-thumbWide.jpg", "widewidth": "190"}, "subtype": "wide", "width": 190, "type": "image"}, {"height": 338, "url": "images/2014/01/02/multimedia/ford-solar/ford-solar-articleLarge.jpg", "legacy": {"xlarge": "images/2014/01/02/multimedia/ford-solar/ford-solar-articleLarge.jpg", "xlargewidth": "600", "xlargeheight": "338"}, "subtype": "xlarge", "width": 600, "type": "image"}, {"height": 75, "url": "images/2014/01/02/multimedia/ford-solar/ford-solar-thumbStandard.jpg", "legacy": {"thumbnail": "images/2014/01/02/multimedia/ford-solar/ford-solar-thumbStandard.jpg", "thumbnailwidth": "75", "thumbnailheight": "75"}, "subtype": "thumbnail", "width": 75, "type": "image"}], "pub_date": "2014-01-02T17:50:37Z", "source": "The New York Times", "news_desk": "Business Day", "keywords": [{"name": "subject", "value": "Solar Energy", "is_major": "N", "rank": "1"}, {"name": "subject", "value": "Automobiles", "is_major": "N", "rank": "2"}, {"name": "organizations", "value": "Ford Motor Co", "is_major": "N", "rank": "3"}], "blog": [], "subsection_name": null, "type_of_material": "Video"}