{"review_count": 324, "image_url": "https://s3-media4.fl.yelpcdn.com/bphoto/JOp-WjNVVCishpNbf0DB4w/o.jpg", "rating": 4.5, "coordinates": {"longitude": -73.98691, "latitude": 40.71873}, "phone": "+12124324180", "categories": [{"alias": "mexican", "title": "Mexican"}, {"alias": "bars", "title": "Bars"}, {"alias": "breakfast_brunch", "title": "Breakfast & Brunch"}], "location": {"city": "New  York", "address3": "", "address2": "", "state": "NY", "address1": "102 Norfolk St", "zip_code": "10002", "country": "US"}, "price": "$$", "is_closed": false, "photos": ["https://s3-media4.fl.yelpcdn.com/bphoto/JOp-WjNVVCishpNbf0DB4w/o.jpg", "https://s3-media2.fl.yelpcdn.com/bphoto/qNawna3WSQwB-OrTbOjBQA/o.jpg", "https://s3-media2.fl.yelpcdn.com/bphoto/pjXn5lYLH3_ze744I9Nn2w/o.jpg"], "url": "https://www.yelp.com/biz/la-contenta-new-york?adjust_creative=92p07_JjKyriZTQxAXRiKQ&utm_campaign=yelp_api_v3&utm_medium=api_v3_business_lookup&utm_source=92p07_JjKyriZTQxAXRiKQ", "id": "la-contenta-new-york", "term": "restaurants", "is_claimed": true, "name": "La  Contenta", "hours": [{"hours_type": "REGULAR", "is_open_now": false, "open": [{"end": "0000", "start": "1600", "is_overnight": false, "day": 0}, {"end": "0000", "start": "1600", "is_overnight": false, "day": 1}, {"end": "0000", "start": "1600", "is_overnight": false, "day": 2}, {"end": "0200", "start": "1100", "is_overnight": true, "day": 3}, {"end": "0200", "start": "1100", "is_overnight": true, "day": 4}, {"end": "0200", "start": "1100", "is_overnight": true, "day": 5}, {"end": "0000", "start": "1100", "is_overnight": false, "day": 6}]}]}