{"slideshow_credits": null, "snippet": "Photographs from Iraq, Pakistan, New York and the Netherlands.", "abstract": "Photographs from Iraq, Pakistan, New York and the Netherlands.", "section_name": "Multimedia", "print_page": null, "document_type": "blogpost", "byline": {"person": [], "original": "By THE NEW YORK TIMES", "organization": "THE NEW YORK TIMES"}, "web_url": "http://lens.blogs.nytimes.com/2012/01/05/pictures-of-the-day-iraq-and-elsewhere-11/", "lead_paragraph": "Photographs from Iraq, Pakistan, New York and the Netherlands.", "headline": {"main": "Pictures of the Day: Iraq and Elsewhere", "kicker": "Lens"}, "_id": "4fd3a3058eb7c8105d8ebbca", "word_count": 14, "multimedia": [], "pub_date": "2012-01-05T17:36:21Z", "source": "The New York Times", "news_desk": null, "keywords": [{"name": "glocations", "value": "Netherlands", "rank": "4"}, {"name": "glocations", "value": "Iraq", "rank": "3"}, {"name": "subject", "value": "Photography", "rank": "2"}, {"name": "glocations", "value": "Pakistan", "rank": "5"}, {"name": "type_of_material", "value": "News", "rank": "1"}], "blog": [], "subsection_name": null, "type_of_material": "Blog"}