{"review_count": 32, "image_url": "https://s3-media4.fl.yelpcdn.com/bphoto/oajAfN3iaB0bIKIIWfUNVg/o.jpg", "rating": 4.0, "coordinates": {"longitude": 2.38941720071012, "latitude": 48.8939850160628}, "phone": "", "photos": ["https://s3-media2.fl.yelpcdn.com/bphoto/oajAfN3iaB0bIKIIWfUNVg/o.jpg", "https://s3-media3.fl.yelpcdn.com/bphoto/2IO6aKSp4vu9OA88kVwb2w/o.jpg", "https://s3-media2.fl.yelpcdn.com/bphoto/HeOthT25QvTNyJSXPgFTlg/o.jpg"], "categories": [{"alias": "parks", "title": "Parks"}], "is_closed": false, "location": {"city": "Paris", "address3": "", "country": "FR", "address1": "211 avenue Jean Jaur\u00e8s", "address2": "", "zip_code": "75019", "state": "75"}, "url": "https://www.yelp.com/biz/parc-de-la-villette-paris?adjust_creative=92p07_JjKyriZTQxAXRiKQ&utm_campaign=yelp_api_v3&utm_medium=api_v3_business_lookup&utm_source=92p07_JjKyriZTQxAXRiKQ", "id": "parc-de-la-villette-paris", "term": "attractions", "name": "Parc de la Villette", "is_claimed": false}