{"review_count": 7, "rating": 5.0, "image_url": "https://s3-media1.fl.yelpcdn.com/bphoto/RN3i-RaYoDWSCnblTl-VQw/o.jpg", "coordinates": {"longitude": -86.8314514, "latitude": 33.5321808}, "phone": "+12059837249", "categories": [{"alias": "soulfood", "title": "Soul Food"}, {"alias": "galleries", "title": "Art Galleries"}], "location": {"city": "Birmingham", "address3": "", "address2": "", "state": "AL", "address1": "317 17th Ave N", "zip_code": "35204", "country": "US"}, "price": "$$", "is_closed": false, "photos": ["https://s3-media1.fl.yelpcdn.com/bphoto/RN3i-RaYoDWSCnblTl-VQw/o.jpg", "https://s3-media1.fl.yelpcdn.com/bphoto/hvg8I0GoxYpixYEPQOD1SA/o.jpg", "https://s3-media1.fl.yelpcdn.com/bphoto/T1lkLEGNgpnNfvTV8fEySQ/o.jpg"], "url": "https://www.yelp.com/biz/gabriellas-bistro-and-art-gallery-birmingham?adjust_creative=92p07_JjKyriZTQxAXRiKQ&utm_campaign=yelp_api_v3&utm_medium=api_v3_business_lookup&utm_source=92p07_JjKyriZTQxAXRiKQ", "id": "gabriellas-bistro-and-art-gallery-birmingham", "term": "restaurants", "name": "GaBriella's Bistro & Art Gallery", "is_claimed": false}