{"review_count": 64, "image_url": "https://s3-media1.fl.yelpcdn.com/bphoto/U7S6bblOgh4mPkRYh5yifA/o.jpg", "rating": 3.5, "coordinates": {"longitude": -0.1409955, "latitude": 51.4945645}, "categories": [{"alias": "tours", "title": "Tours"}], "location": {"city": "London", "address3": "", "country": "GB", "address1": "258 Vauxhall Bridge Road", "address2": "", "zip_code": "SW1V 1BS", "state": "XGL"}, "phone": "+442079501777", "is_closed": false, "photos": ["https://s3-media2.fl.yelpcdn.com/bphoto/U7S6bblOgh4mPkRYh5yifA/o.jpg", "https://s3-media2.fl.yelpcdn.com/bphoto/diYNAgxglr7jK6JqxC3wGw/o.jpg", "https://s3-media1.fl.yelpcdn.com/bphoto/MF_dy62vzsk6Evsflt76Aw/o.jpg"], "url": "https://www.yelp.com/biz/evan-evans-tours-london?adjust_creative=92p07_JjKyriZTQxAXRiKQ&utm_campaign=yelp_api_v3&utm_medium=api_v3_business_lookup&utm_source=92p07_JjKyriZTQxAXRiKQ", "id": "evan-evans-tours-london", "term": "attractions", "hours": [{"hours_type": "REGULAR", "is_open_now": false, "open": [{"end": "1900", "start": "0700", "is_overnight": false, "day": 0}, {"end": "1900", "start": "0700", "is_overnight": false, "day": 1}, {"end": "1900", "start": "0700", "is_overnight": false, "day": 2}, {"end": "1900", "start": "0700", "is_overnight": false, "day": 3}, {"end": "1900", "start": "0700", "is_overnight": false, "day": 4}, {"end": "1900", "start": "0700", "is_overnight": false, "day": 5}, {"end": "1900", "start": "0700", "is_overnight": false, "day": 6}]}], "name": "Evan Evans Tours", "is_claimed": true}