{"review_count": 55, "image_url": "https://s3-media2.fl.yelpcdn.com/bphoto/wPHfmDiWVnzXtfkI3gdUCA/o.jpg", "rating": 3.5, "coordinates": {"longitude": -95.5176897287259, "latitude": 29.7022601912284}, "phone": "+17137725900", "categories": [{"alias": "musicvenues", "title": "Music Venues"}, {"alias": "venues", "title": "Venues & Event Spaces"}], "location": {"city": "Houston", "address3": "", "country": "US", "address1": "7326 SW Fwy", "address2": "", "zip_code": "77074", "state": "TX"}, "price": "$$", "is_closed": false, "photos": ["https://s3-media3.fl.yelpcdn.com/bphoto/wPHfmDiWVnzXtfkI3gdUCA/o.jpg", "https://s3-media3.fl.yelpcdn.com/bphoto/tIpVWKyN3z3SZk6-fuYmQA/o.jpg", "https://s3-media3.fl.yelpcdn.com/bphoto/0ARs6_FbxDV0H-WJClIpdQ/o.jpg"], "url": "https://www.yelp.com/biz/arena-theatre-houston?adjust_creative=92p07_JjKyriZTQxAXRiKQ&utm_campaign=yelp_api_v3&utm_medium=api_v3_business_lookup&utm_source=92p07_JjKyriZTQxAXRiKQ", "id": "arena-theatre-houston", "term": "attractions", "is_claimed": true, "name": "Arena Theatre", "hours": [{"hours_type": "REGULAR", "is_open_now": false, "open": [{"end": "1800", "start": "1000", "is_overnight": false, "day": 0}, {"end": "1800", "start": "1000", "is_overnight": false, "day": 1}, {"end": "1800", "start": "1000", "is_overnight": false, "day": 2}, {"end": "1800", "start": "1000", "is_overnight": false, "day": 3}, {"end": "1800", "start": "1000", "is_overnight": false, "day": 4}]}]}