{"review_count": 33, "rating": 4.0, "image_url": "https://s3-media1.fl.yelpcdn.com/bphoto/uLQtSqW9SvX2s9DKMm3u5Q/o.jpg", "coordinates": {"longitude": 115.877317635664, "latitude": -31.9613943312085}, "phone": "+61892610035", "categories": [{"alias": "raw_food", "title": "Live/Raw Food"}, {"alias": "vegetarian", "title": "Vegetarian"}, {"alias": "modern_australian", "title": "Modern Australian"}], "location": {"city": "East Perth", "address3": "", "country": "AU", "address1": "10 Adelaide Terrace", "address2": "", "zip_code": "6004", "state": "WA"}, "price": "$$$", "is_closed": false, "photos": ["https://s3-media3.fl.yelpcdn.com/bphoto/uLQtSqW9SvX2s9DKMm3u5Q/o.jpg", "https://s3-media3.fl.yelpcdn.com/bphoto/0aXRLkwwhVv6zkahZ1HaXg/o.jpg", "https://s3-media1.fl.yelpcdn.com/bphoto/hJCUu_rKdLqEIuhMsdw0IA/o.jpg"], "url": "https://www.yelp.com/biz/heirloom-east-perth?adjust_creative=92p07_JjKyriZTQxAXRiKQ&utm_campaign=yelp_api_v3&utm_medium=api_v3_business_lookup&utm_source=92p07_JjKyriZTQxAXRiKQ", "id": "heirloom-east-perth", "term": "restaurants", "is_claimed": false, "name": "Heirloom", "hours": [{"open": [{"end": "1430", "start": "0600", "is_overnight": false, "day": 0}, {"end": "2130", "start": "1700", "is_overnight": false, "day": 0}, {"end": "1430", "start": "0600", "is_overnight": false, "day": 1}, {"end": "2130", "start": "1700", "is_overnight": false, "day": 1}, {"end": "1430", "start": "0600", "is_overnight": false, "day": 2}, {"end": "2130", "start": "1700", "is_overnight": false, "day": 2}, {"end": "1430", "start": "0600", "is_overnight": false, "day": 3}, {"end": "2130", "start": "1700", "is_overnight": false, "day": 3}, {"end": "1430", "start": "0600", "is_overnight": false, "day": 4}, {"end": "2130", "start": "1700", "is_overnight": false, "day": 4}, {"end": "1430", "start": "0700", "is_overnight": false, "day": 5}, {"end": "2130", "start": "1700", "is_overnight": false, "day": 5}, {"end": "1430", "start": "0700", "is_overnight": false, "day": 6}, {"end": "2130", "start": "1700", "is_overnight": false, "day": 6}], "is_open_now": true, "hours_type": "REGULAR"}]}