{"review_count": 2, "rating": 3.5, "image_url": "https://s3-media3.fl.yelpcdn.com/bphoto/lUtQnPt_oce3oJO8xF2xRw/o.jpg", "coordinates": {"longitude": 149.1320038, "latitude": -35.2822304}, "categories": [{"alias": "cafes", "title": "Cafes"}], "location": {"city": "Canberra City", "address3": null, "country": "AU", "address1": "London Cct", "address2": null, "zip_code": "2601", "state": "ACT"}, "phone": "+61262578501", "is_closed": false, "photos": ["https://s3-media4.fl.yelpcdn.com/bphoto/lUtQnPt_oce3oJO8xF2xRw/o.jpg"], "url": "https://www.yelp.com/biz/hogs-breath-cafe-canberra-city?adjust_creative=92p07_JjKyriZTQxAXRiKQ&utm_campaign=yelp_api_v3&utm_medium=api_v3_business_lookup&utm_source=92p07_JjKyriZTQxAXRiKQ", "id": "hogs-breath-cafe-canberra-city", "term": "restaurants", "name": "Hog's Breath Cafe", "is_claimed": false}