{"review_count": 140, "image_url": "https://s3-media3.fl.yelpcdn.com/bphoto/bq1wnHaptYLXuwQIRLpL0w/o.jpg", "rating": 4.5, "coordinates": {"longitude": -73.9895794188884, "latitude": 40.7412290453689}, "categories": [{"alias": "landmarks", "title": "Landmarks & Historical Buildings"}], "location": {"city": "New York", "address3": "", "country": "US", "address1": "175 5th Ave", "address2": "", "zip_code": "10010", "state": "NY"}, "phone": "", "is_closed": false, "photos": ["https://s3-media2.fl.yelpcdn.com/bphoto/bq1wnHaptYLXuwQIRLpL0w/o.jpg", "https://s3-media3.fl.yelpcdn.com/bphoto/r6ybYmqq-fiRYGa3ULg_yw/o.jpg", "https://s3-media2.fl.yelpcdn.com/bphoto/ZfLEVlWa_JXHY-Hzj9OSew/o.jpg"], "url": "https://www.yelp.com/biz/flatiron-building-new-york-2?adjust_creative=92p07_JjKyriZTQxAXRiKQ&utm_campaign=yelp_api_v3&utm_medium=api_v3_business_lookup&utm_source=92p07_JjKyriZTQxAXRiKQ", "id": "flatiron-building-new-york-2", "term": "attractions", "name": "Flatiron Building", "is_claimed": false}