{"review_count": 385, "image_url": "https://s3-media3.fl.yelpcdn.com/bphoto/Tgx_XEs_Yd5yy8LCHRB76A/o.jpg", "rating": 3.5, "coordinates": {"longitude": -121.8859863, "latitude": 37.3306007}, "phone": "+14082806161", "categories": [{"alias": "cafes", "title": "Cafes"}, {"alias": "newamerican", "title": "American (New)"}, {"alias": "musicvenues", "title": "Music Venues"}], "location": {"city": "San Jose", "address3": "", "address2": "", "state": "CA", "address1": "374 S 1st St", "zip_code": "95113", "country": "US"}, "price": "$$", "is_closed": false, "photos": ["https://s3-media3.fl.yelpcdn.com/bphoto/Tgx_XEs_Yd5yy8LCHRB76A/o.jpg", "https://s3-media4.fl.yelpcdn.com/bphoto/3Gc7J-iMFliqyhnyjpnEBA/o.jpg", "https://s3-media2.fl.yelpcdn.com/bphoto/4yfYcHE_0pCWdUNUJ4Pf7w/o.jpg"], "url": "https://www.yelp.com/biz/cafe-stritch-san-jose?adjust_creative=92p07_JjKyriZTQxAXRiKQ&utm_campaign=yelp_api_v3&utm_medium=api_v3_business_lookup&utm_source=92p07_JjKyriZTQxAXRiKQ", "id": "cafe-stritch-san-jose", "term": "restaurants", "hours": [{"hours_type": "REGULAR", "is_open_now": true, "open": [{"end": "0200", "start": "1600", "is_overnight": true, "day": 2}, {"end": "0200", "start": "1600", "is_overnight": true, "day": 3}, {"end": "0200", "start": "1600", "is_overnight": true, "day": 4}, {"end": "0200", "start": "1600", "is_overnight": true, "day": 5}, {"end": "0000", "start": "1600", "is_overnight": false, "day": 6}]}], "name": "Cafe Stritch", "is_claimed": true}