{"review_count": 140, "image_url": "https://s3-media4.fl.yelpcdn.com/bphoto/V_SKqsN-oFXG9ubxZDtnHQ/o.jpg", "rating": 4.0, "coordinates": {"longitude": -105.000548015939, "latitude": 39.748375254531}, "phone": "+13038002652", "categories": [{"alias": "bars", "title": "Bars"}, {"alias": "german", "title": "German"}, {"alias": "pretzels", "title": "Pretzels"}], "location": {"city": "Denver", "address3": null, "address2": null, "state": "CO", "address1": "1415 Market St", "zip_code": "80202", "country": "US"}, "price": "$$", "is_closed": false, "photos": ["https://s3-media1.fl.yelpcdn.com/bphoto/V_SKqsN-oFXG9ubxZDtnHQ/o.jpg", "https://s3-media3.fl.yelpcdn.com/bphoto/WIi2XU2chQsrrbTuCEsoFQ/o.jpg", "https://s3-media4.fl.yelpcdn.com/bphoto/eP9cY4S8Lxl1nJqWFkTueA/o.jpg"], "url": "https://www.yelp.com/biz/rhein-haus-denver-denver-2?adjust_creative=92p07_JjKyriZTQxAXRiKQ&utm_campaign=yelp_api_v3&utm_medium=api_v3_business_lookup&utm_source=92p07_JjKyriZTQxAXRiKQ", "id": "rhein-haus-denver-denver-2", "term": "restaurants", "is_claimed": true, "name": "Rhein Haus Denver", "hours": [{"hours_type": "REGULAR", "is_open_now": true, "open": [{"end": "2300", "start": "1100", "is_overnight": false, "day": 0}, {"end": "2300", "start": "1100", "is_overnight": false, "day": 1}, {"end": "2300", "start": "1100", "is_overnight": false, "day": 2}, {"end": "2300", "start": "1100", "is_overnight": false, "day": 3}, {"end": "0200", "start": "1100", "is_overnight": true, "day": 4}, {"end": "0200", "start": "1100", "is_overnight": true, "day": 5}, {"end": "2300", "start": "1000", "is_overnight": false, "day": 6}]}]}