{"type_of_material": "News", "print_page": 0, "_id": "58baea4d95d0e024902fd888", "headline": {"main": "Famine-Hit South Sudan Sharply Raises Foreigners' Work Fees", "print_headline": "Famine-Hit South Sudan Sharply Raises Foreigners' Work Fees"}, "blog": [], "lead_paragraph": "South Sudan has sharply increased the fees required for foreigners to work in the country &#8212; from roughly $100 to up to $10,000 &#8212; just days after famine was declared there.", "document_type": "article", "snippet": "South Sudan has sharply increased the fees required for foreigners to work in the country &#8212; from roughly $100 to up to $10,000 &#8212; just days after famine was declared there....", "section_name": "World", "web_url": "https://www.nytimes.com/aponline/2017/03/04/world/africa/ap-af-south-sudan-famine.html", "byline": {"organization": "THE ASSOCIATED PRESS", "original": "By THE ASSOCIATED PRESS", "person": []}, "word_count": 364, "keywords": [], "abstract": null, "slideshow_credits": null, "subsection_name": "Africa", "source": "AP", "pub_date": "2017-03-04T16:24:41+0000", "multimedia": [], "news_desk": "None"}