{"type_of_material": "News", "print_page": 0, "_id": "58bb9fbd95d0e024902fd989", "headline": {"main": "Sam Querrey Beats Rafael Nadal in Mexican Open Final", "print_headline": "Sam Querrey Beats Rafael Nadal in Mexican Open Final"}, "blog": [], "lead_paragraph": "American Sam Querrey used a strong serve to beat Rafael Nadal 6-3, 7-6 (3) on Saturday night in the Mexican Open final.", "document_type": "article", "snippet": "American Sam Querrey used a strong serve to beat Rafael Nadal 6-3, 7-6 (3) on Saturday night in the Mexican Open final....", "section_name": "Sports", "web_url": "https://www.nytimes.com/aponline/2017/03/05/sports/tennis/ap-ten-acapulco.html", "byline": {"organization": "THE ASSOCIATED PRESS", "original": "By THE ASSOCIATED PRESS", "person": []}, "word_count": 136, "keywords": [], "abstract": null, "slideshow_credits": null, "subsection_name": "Tennis", "source": "AP", "pub_date": "2017-03-05T05:18:42+0000", "multimedia": [], "news_desk": "None"}