{"type_of_material": "News", "print_page": 0, "_id": "58bbda0d95d0e024902fd9ba", "headline": {"main": "Wave of IS Car Bombs Targets Iraqi Troops in West Mosul", "print_headline": "Wave of IS Car Bombs Targets Iraqi Troops in West Mosul"}, "blog": [], "lead_paragraph": "Iraqi troops encountered the heaviest clashes yet with Islamic State group fighters Sunday in western Mosul since the start of the new push more than two weeks ago, according to a senior commander.", "document_type": "article", "snippet": "Iraqi troops encountered the heaviest clashes yet with Islamic State group fighters Sunday in western Mosul since the start of the new push more than two weeks ago, according to a senior commander....", "section_name": "World", "web_url": "https://www.nytimes.com/aponline/2017/03/05/world/middleeast/ap-ml-iraq.html", "byline": {"organization": "THE ASSOCIATED PRESS", "original": "By THE ASSOCIATED PRESS", "person": []}, "word_count": 382, "keywords": [], "abstract": null, "slideshow_credits": null, "subsection_name": "Middle East", "source": "AP", "pub_date": "2017-03-05T09:27:36+0000", "multimedia": [], "news_desk": "None"}