{"type_of_material": "News", "print_page": 0, "_id": "58bcb41a95d0e024902fdac0", "headline": {"main": "Cold Putter Prevents McIlroy From Challenging in Mexico", "print_headline": "Cold Putter Prevents McIlroy From Challenging in Mexico"}, "blog": [], "lead_paragraph": "Rory McIlroy never looked like he would regain his world number one ranking on Sunday as a cold putter prevented him from mounting a challenge in the final round at the WGC-Mexico Championship.", "document_type": "article", "snippet": "Rory McIlroy never looked like he would regain his world number one ranking on Sunday as a cold putter prevented him from mounting a challenge in the final round at the WGC-Mexico Championship....", "section_name": "Sports", "web_url": "https://www.nytimes.com/reuters/2017/03/05/sports/golf/05reuters-golf-pga-mcilroy.html", "byline": {"organization": "REUTERS", "original": "By REUTERS", "person": []}, "word_count": 333, "keywords": [], "abstract": null, "slideshow_credits": null, "subsection_name": "Golf", "source": "Reuters", "pub_date": "2017-03-06T00:57:28+0000", "multimedia": [], "news_desk": "None"}