{"type_of_material": "News", "print_page": 0, "_id": "58bc3bca95d0e024902fda32", "headline": {"main": "Bruno Mars, Justin Timberlake Shine at iHeartRadio Awards", "print_headline": "Bruno Mars, Justin Timberlake Shine at iHeartRadio Awards"}, "blog": [], "lead_paragraph": "The 2017 iHeartRadio Music Awards started with Justin Timberlake speaking about inclusion and dedicating his award to children who feel different, and ended with a rousing performance by Bruno Mars that included crowd participation from Florida Georgia Line, Thomas Rhett, Ty Dolla $ign, Heidi Klum and more.", "document_type": "article", "snippet": "The 2017 iHeartRadio Music Awards started with Justin Timberlake speaking about inclusion and dedicating his award to children who feel different, and ended with a rousing performance by Bruno Mars that included crowd participation from Florida Ge...", "section_name": "U.S.", "web_url": "https://www.nytimes.com/aponline/2017/03/05/us/ap-us-music-iheartradio-awards.html", "byline": {"organization": "THE ASSOCIATED PRESS", "original": "By THE ASSOCIATED PRESS", "person": []}, "word_count": 778, "keywords": [], "abstract": null, "slideshow_credits": null, "subsection_name": null, "source": "AP", "pub_date": "2017-03-05T16:24:39+0000", "multimedia": [], "news_desk": "None"}