{"type_of_material": "News", "print_page": 0, "_id": "58bc92fc95d0e024902fda94", "headline": {"main": "Some Marines Being Investigated for Sharing Nude Photos", "print_headline": "Some Marines Being Investigated for Sharing Nude Photos"}, "blog": [], "lead_paragraph": "The Defense Department is investigating reports that some Marines shared naked photographs of female Marines, veterans and other women on a secret Facebook page, some of which were taken without their knowledge.", "document_type": "article", "snippet": "The Defense Department is investigating reports that some Marines shared naked photographs of female Marines, veterans and other women on a secret Facebook page, some of which were taken without their knowledge....", "section_name": "U.S.", "web_url": "https://www.nytimes.com/aponline/2017/03/05/us/politics/ap-us-marines-nude-photos.html", "byline": {"organization": "THE ASSOCIATED PRESS", "original": "By THE ASSOCIATED PRESS", "person": []}, "word_count": 604, "keywords": [], "abstract": null, "slideshow_credits": null, "subsection_name": "Politics", "source": "AP", "pub_date": "2017-03-05T22:36:40+0000", "multimedia": [], "news_desk": "None"}