{"review_count": 3, "image_url": "", "rating": 4.0, "coordinates": {"longitude": 149.0937042, "latitude": -35.239399}, "categories": [{"alias": "cafes", "title": "Cafes"}, {"alias": "catering", "title": "Caterers"}], "location": {"city": "Bruce", "address3": null, "country": "AU", "address1": "Thynne St", "address2": null, "zip_code": "2617", "state": "ACT"}, "phone": "+61262534964", "is_closed": false, "photos": [], "url": "https://www.yelp.com/biz/cafe-momo-bruce-2?adjust_creative=92p07_JjKyriZTQxAXRiKQ&utm_campaign=yelp_api_v3&utm_medium=api_v3_business_lookup&utm_source=92p07_JjKyriZTQxAXRiKQ", "id": "cafe-momo-bruce-2", "term": "restaurants", "name": "Cafe Momo", "is_claimed": false}