{"slideshow_credits": null, "snippet": "Fashion news we're reading, from Moda Operandi's expansion to Georgina Chapman's collaboration with the N.F.L.", "abstract": "Fashion news we're reading, from Moda Operandi's expansion to Georgina Chapman's collaboration with the N.F.L.", "section_name": "Style", "print_page": null, "document_type": "blogpost", "byline": {"person": [], "original": "By THE NEW YORK TIMES", "organization": "The New York Times"}, "web_url": "http://runway.blogs.nytimes.com/2012/06/12/fashion-news-were-reading-now-7/", "lead_paragraph": null, "headline": {"main": "Fashion News We're Reading Now", "kicker": "On the Runway"}, "_id": "4fdf29c832439115e30b70ae", "word_count": "159", "multimedia": [], "pub_date": "2012-06-12T19:28:13Z", "source": "The New York Times", "news_desk": null, "keywords": [], "blog": [], "subsection_name": "Fashion &amp; Style", "type_of_material": "Blog"}