{"review_count": 19, "image_url": "https://s3-media4.fl.yelpcdn.com/bphoto/ygfaTDa6BMpnYpzmM3kmoQ/o.jpg", "rating": 3.0, "coordinates": {"longitude": -115.167984, "latitude": 36.126976}, "categories": [{"alias": "theater", "title": "Performing Arts"}], "location": {"city": "Las Vegas", "address3": "", "country": "US", "address1": "3131 Las Vegas Blvd. South", "address2": "", "zip_code": "89109", "state": "NV"}, "phone": "+17027703392", "is_closed": false, "photos": ["https://s3-media4.fl.yelpcdn.com/bphoto/ygfaTDa6BMpnYpzmM3kmoQ/o.jpg", "https://s3-media2.fl.yelpcdn.com/bphoto/FIaP7-gVn0PRi0fa0gAF-Q/o.jpg", "https://s3-media4.fl.yelpcdn.com/bphoto/0HNfPy4bhbT7VL45X5SZLg/o.jpg"], "url": "https://www.yelp.com/biz/lake-of-dreams-las-vegas?adjust_creative=92p07_JjKyriZTQxAXRiKQ&utm_campaign=yelp_api_v3&utm_medium=api_v3_business_lookup&utm_source=92p07_JjKyriZTQxAXRiKQ", "id": "lake-of-dreams-las-vegas", "term": "attractions", "name": "Lake of Dreams", "is_claimed": true}