{"slideshow_credits": null, "snippet": "Corrections appearing in print on September 9, 2012.", "abstract": null, "section_name": "Corrections", "print_page": "3", "document_type": "article", "byline": [], "web_url": "http://www.nytimes.com/2012/09/09/pageoneplus/corrections-september-9-2012.html", "lead_paragraph": "Corrections appearing in print on September 9, 2012.", "headline": {"main": "Corrections: September 9, 2012", "print_headline": "Corrections"}, "_id": "5050cc941c22dfde670c63ad", "word_count": "968", "multimedia": [], "pub_date": "2012-09-09T00:00:00Z", "source": "The New York Times", "news_desk": "Summary", "keywords": [], "blog": [], "subsection_name": null, "type_of_material": "Correction"}