{"slideshow_credits": null, "snippet": "The more details that are released about the budget sequester scheduled for next year, the worse it looks.", "abstract": "Editorial holds that the more details that are released about the budget sequester scheduled for 2013, the worse it looks; warns that nearly every government function will be significantly diminished, alongside defense spending; urges Congress to cancel the ham-handed reductions and negotiate a realistic plan to balance spending cuts with tax increases on the rich.", "section_name": "Opinion", "print_page": "22", "document_type": "article", "byline": [], "web_url": "http://www.nytimes.com/2012/09/15/opinion/cutting-government-blindfolded.html", "lead_paragraph": "The more details that are released about the budget sequester scheduled for next year, the worse it looks.", "headline": {"seo": "Cutting Government, Blindfolded", "main": "Cutting Government, Blindfolded", "print_headline": "Cutting Government, Blindfolded", "content_kicker": "Editorial", "kicker": "Editorial"}, "_id": "5053d7321c22dfde670c8a95", "word_count": "449", "multimedia": [], "pub_date": "2012-09-15T00:00:00Z", "source": "The New York Times", "news_desk": "Editorial", "keywords": [{"value": "Federal Budget (US)", "name": "subject", "is_major": "Y", "rank": "1"}, {"value": "Romney, Mitt", "name": "persons", "is_major": "N", "rank": "2"}, {"value": "Obama, Barack", "name": "persons", "is_major": "N", "rank": "3"}, {"value": "Presidential Election of 2012", "name": "subject", "is_major": "N", "rank": "4"}, {"value": "Senate", "name": "organizations", "is_major": "N", "rank": "5"}, {"value": "House of Representatives", "name": "organizations", "is_major": "N", "rank": "6"}, {"value": "United States Defense and Military Forces", "name": "subject", "is_major": "N", "rank": "7"}, {"value": "Defense Department", "name": "organizations", "is_major": "N", "rank": "8"}, {"value": "Editorials", "name": "subject", "is_major": "Y", "rank": "9"}], "blog": [], "subsection_name": null, "type_of_material": "Editorial"}