{"slideshow_credits": null, "snippet": "See a secret hangout during the Communist regime and more in this tour of the Bulgarian capital.", "abstract": null, "section_name": "Travel", "print_page": null, "document_type": "multimedia", "byline": [], "web_url": "http://www.nytimes.com/slideshow/2012/09/02/travel/02SOFIA.html", "lead_paragraph": "See a secret hangout during the Communist regime and more in this tour of the Bulgarian capital.", "headline": {"main": "Scenes From Sofia, Bulgaria"}, "_id": "513e03e9cf28d04ae00017ce", "word_count": "17", "multimedia": [{"height": 126, "url": "images/2012/09/02/travel/02SOFIA-slide-7DMD/02SOFIA-slide-7DMD-thumbWide.jpg", "legacy": {"wideheight": "126", "wide": "images/2012/09/02/travel/02SOFIA-slide-7DMD/02SOFIA-slide-7DMD-thumbWide.jpg", "widewidth": "190"}, "subtype": "wide", "width": 190, "type": "image"}, {"height": 75, "url": "images/2012/09/02/travel/02SOFIA-slide-7DMD/02SOFIA-slide-7DMD-thumbStandard.jpg", "legacy": {"thumbnail": "images/2012/09/02/travel/02SOFIA-slide-7DMD/02SOFIA-slide-7DMD-thumbStandard.jpg", "thumbnailwidth": "75", "thumbnailheight": "75"}, "subtype": "thumbnail", "width": 75, "type": "image"}], "pub_date": "2012-09-02T00:00:00Z", "source": "The New York Times", "news_desk": "Travel", "keywords": [{"name": "subject", "value": "Travel and Vacations", "is_major": "N", "rank": "1"}, {"name": "glocations", "value": "Sofia (Bulgaria)", "is_major": "N", "rank": "2"}], "blog": [], "subsection_name": null, "type_of_material": "Slideshow"}