{"review_count": 1, "image_url": "", "rating": 4.0, "coordinates": {"longitude": 149.064890251113, "latitude": -35.2378148194433}, "phone": "+61262519850", "categories": [{"alias": "mexican", "title": "Mexican"}], "location": {"city": "Belconnen", "address3": "", "country": "AU", "address1": "Level 3", "address2": "18 Benjamin Way,  Westfield Belconnen", "zip_code": "2617", "state": "ACT"}, "price": "$", "is_closed": false, "photos": [], "url": "https://www.yelp.com/biz/mad-mex-belconnen?adjust_creative=92p07_JjKyriZTQxAXRiKQ&utm_campaign=yelp_api_v3&utm_medium=api_v3_business_lookup&utm_source=92p07_JjKyriZTQxAXRiKQ", "id": "mad-mex-belconnen", "term": "restaurants", "name": "Mad Mex", "is_claimed": false}