{"slideshow_credits": null, "snippet": "Let us know whether you agree with choices like \u201cBirdman\u201d and \u201cBoyhood,\u201d or would go with something else altogether.", "abstract": "Let us know whether you agree with choices like \u201cBirdman\u201d and \u201cBoyhood,\u201d or would go with something else altogether.", "section_name": null, "print_page": null, "document_type": "blogpost", "byline": {"person": [], "original": "By THE NEW YORK TIMES", "organization": "The New York Times"}, "web_url": "http://carpetbagger.blogs.nytimes.com/2014/12/03/whats-your-pick-for-best-picture/", "lead_paragraph": null, "headline": {"main": "What's Your Pick for Best Picture?", "kicker": "Carpetbagger"}, "_id": "547f257938f0d84a61c0fa40", "word_count": "125", "multimedia": [], "pub_date": "2014-12-03T09:58:22Z", "source": "The New York Times", "news_desk": "Culture", "keywords": [], "blog": [], "subsection_name": null, "type_of_material": "Blog"}