{"slideshow_credits": null, "snippet": "Readers discuss reforms to make the organization more effective.", "abstract": null, "section_name": "Opinion", "print_page": "8", "document_type": "article", "byline": [], "web_url": "http://www.nytimes.com/2014/12/14/opinion/creating-a-stronger-un.html", "lead_paragraph": "Readers discuss reforms to make the organization more effective.", "headline": {"main": " Creating a Stronger U.N. ", "print_headline": "Creating a Stronger U.N.", "content_kicker": "Sunday Dialogue", "kicker": "Sunday Dialogue"}, "_id": "548c93c538f0d80cddf9f653", "word_count": "1729", "multimedia": [{"height": 126, "url": "images/2014/12/14/sunday-review/l14dialogue/l14dialogue-thumbWide.jpg", "legacy": {"wideheight": "126", "wide": "images/2014/12/14/sunday-review/l14dialogue/l14dialogue-thumbWide.jpg", "widewidth": "190"}, "subtype": "wide", "width": 190, "type": "image"}, {"height": 600, "url": "images/2014/12/14/sunday-review/l14dialogue/l14dialogue-articleLarge.jpg", "legacy": {"xlarge": "images/2014/12/14/sunday-review/l14dialogue/l14dialogue-articleLarge.jpg", "xlargewidth": "600", "xlargeheight": "600"}, "subtype": "xlarge", "width": 600, "type": "image"}, {"height": 75, "url": "images/2014/12/14/sunday-review/l14dialogue/l14dialogue-thumbStandard.jpg", "legacy": {"thumbnail": "images/2014/12/14/sunday-review/l14dialogue/l14dialogue-thumbStandard.jpg", "thumbnailwidth": "75", "thumbnailheight": "75"}, "subtype": "thumbnail", "width": 75, "type": "image"}], "pub_date": "2014-12-14T00:00:00Z", "source": "The New York Times", "news_desk": "Letters", "keywords": [{"value": "United Nations", "name": "organizations", "is_major": "N", "rank": "1"}, {"value": "Security Council (UN)", "name": "organizations", "is_major": "N", "rank": "2"}, {"value": "International Court of Justice (UN)", "name": "organizations", "is_major": "N", "rank": "3"}, {"value": "Al Qaeda", "name": "organizations", "is_major": "N", "rank": "4"}, {"value": "Islamic State in Iraq and Syria (ISIS)", "name": "organizations", "is_major": "N", "rank": "5"}], "blog": [], "subsection_name": null, "type_of_material": "Letter"}